{
  "index": 4,
  "blueprint": {
    "item": "blueprint",
    "label": "Accumulator Bank",
    "shift_x": 281,
    "shift_y": -41,
    "version": 562949955387393,
    "entities": [
      {"name": "accumulator", "position": {"x": 2, "y": 0}},
      {"name": "accumulator", "position": {"x": 0, "y": 2}},
      {"name": "accumulator", "position": {"x": 2, "y": 2}},
      {"name": "accumulator", "position": {"x": 4, "y": 0}},
      {"name": "accumulator", "position": {"x": 6, "y": 0}},
      {"name": "accumulator", "position": {"x": 4, "y": 2}},
      {"name": "accumulator", "position": {"x": 6, "y": 2}},
      {"name": "accumulator", "position": {"x": 0, "y": 4}},
      {"name": "accumulator", "position": {"x": 2, "y": 4}},
      {"name": "accumulator", "position": {"x": 0, "y": 6}},
      {"name": "accumulator", "position": {"x": 2, "y": 6}},
      {"name": "accumulator", "position": {"x": 4, "y": 4}},
      {"name": "accumulator", "position": {"x": 6, "y": 4}},
      {"name": "accumulator", "position": {"x": 4, "y": 6}},
      {"name": "accumulator", "position": {"x": 6, "y": 6}},
      {"name": "accumulator", "position": {"x": 8, "y": 0}},
      {"name": "accumulator", "position": {"x": 10, "y": 0}},
      {"name": "accumulator", "position": {"x": 8, "y": 2}},
      {"name": "accumulator", "position": {"x": 10, "y": 2}},
      {"name": "accumulator", "position": {"x": 12, "y": 0}},
      {"name": "accumulator", "position": {"x": 14, "y": 0}},
      {"name": "accumulator", "position": {"x": 12, "y": 2}},
      {"name": "accumulator", "position": {"x": 14, "y": 2}},
      {"name": "accumulator", "position": {"x": 8, "y": 4}},
      {"name": "accumulator", "position": {"x": 10, "y": 4}},
      {"name": "accumulator", "position": {"x": 8, "y": 6}},
      {"name": "accumulator", "position": {"x": 10, "y": 6}},
      {"name": "accumulator", "position": {"x": 12, "y": 4}},
      {"name": "accumulator", "position": {"x": 14, "y": 4}},
      {"name": "accumulator", "position": {"x": 12, "y": 6}},
      {"name": "accumulator", "position": {"x": 14, "y": 6}},
      {"name": "accumulator", "position": {"x": 0, "y": 8}},
      {"name": "accumulator", "position": {"x": 2, "y": 8}},
      {"name": "accumulator", "position": {"x": 0, "y": 10}},
      {"name": "accumulator", "position": {"x": 2, "y": 10}},
      {"name": "accumulator", "position": {"x": 4, "y": 8}},
      {"name": "accumulator", "position": {"x": 6, "y": 8}},
      {"name": "accumulator", "position": {"x": 4, "y": 10}},
      {"name": "accumulator", "position": {"x": 6, "y": 10}},
      {"name": "accumulator", "position": {"x": 0, "y": 12}},
      {"name": "accumulator", "position": {"x": 2, "y": 12}},
      {"name": "accumulator", "position": {"x": 0, "y": 14}},
      {"name": "accumulator", "position": {"x": 2, "y": 14}},
      {"name": "accumulator", "position": {"x": 4, "y": 12}},
      {"name": "accumulator", "position": {"x": 6, "y": 12}},
      {"name": "accumulator", "position": {"x": 4, "y": 14}},
      {"name": "accumulator", "position": {"x": 6, "y": 14}},
      {"name": "accumulator", "position": {"x": 10, "y": 8}},
      {"name": "accumulator", "position": {"x": 8, "y": 10}},
      {"name": "accumulator", "position": {"x": 10, "y": 10}},
      {"name": "accumulator", "position": {"x": 12, "y": 8}},
      {"name": "accumulator", "position": {"x": 14, "y": 8}},
      {"name": "accumulator", "position": {"x": 12, "y": 10}},
      {"name": "accumulator", "position": {"x": 14, "y": 10}},
      {"name": "accumulator", "position": {"x": 8, "y": 12}},
      {"name": "accumulator", "position": {"x": 10, "y": 12}},
      {"name": "accumulator", "position": {"x": 8, "y": 14}},
      {"name": "accumulator", "position": {"x": 10, "y": 14}},
      {"name": "accumulator", "position": {"x": 12, "y": 12}},
      {"name": "accumulator", "position": {"x": 14, "y": 12}},
      {"name": "accumulator", "position": {"x": 12, "y": 14}},
      {"name": "accumulator", "position": {"x": 14, "y": 14}},
      {"name": "accumulator", "position": {"x": 16, "y": 0}},
      {"name": "accumulator", "position": {"x": 16, "y": 2}},
      {"name": "accumulator", "position": {"x": 16, "y": 4}},
      {"name": "accumulator", "position": {"x": 16, "y": 6}},
      {"name": "accumulator", "position": {"x": 16, "y": 8}},
      {"name": "accumulator", "position": {"x": 16, "y": 10}},
      {"name": "accumulator", "position": {"x": 16, "y": 12}},
      {"name": "accumulator", "position": {"x": 16, "y": 14}},
      {"name": "accumulator", "position": {"x": 0, "y": 16}},
      {"name": "accumulator", "position": {"x": 2, "y": 16}},
      {"name": "accumulator", "position": {"x": 4, "y": 16}},
      {"name": "accumulator", "position": {"x": 6, "y": 16}},
      {"name": "accumulator", "position": {"x": 8, "y": 16}},
      {"name": "accumulator", "position": {"x": 10, "y": 16}},
      {"name": "accumulator", "position": {"x": 12, "y": 16}},
      {"name": "accumulator", "position": {"x": 14, "y": 16}},
      {"name": "accumulator", "position": {"x": 16, "y": 16}},
      {"name": "lightning-rod", "position": {"x": -0.5, "y": -0.5}},
      {"name": "substation", "position": {"x": 8, "y": 8}}
    ],
    "icons": [{"index": 1, "signal": {"name": "accumulator"}}]
  }
}
