{
  "index": 13,
  "blueprint": {
    "item": "blueprint",
    "label": "2-Car (right output) Requester",
    "shift_x": -871,
    "shift_y": -122,
    "version": 562949955518464,
    "entities": [
      {
        "name": "arithmetic-combinator",
        "control_behavior": {
          "arithmetic_conditions": {
            "operation": "/",
            "second_constant": -24,
            "first_signal": {"name": "signal-each", "type": "virtual"},
            "output_signal": {"name": "signal-each", "type": "virtual"}
          }
        },
        "position": {"x": -2.5, "y": 6}
      },
      {"name": "big-electric-pole", "position": {"x": -10, "y": 5}},
      {
        "name": "bulk-inserter",
        "direction": 8,
        "control_behavior": {
          "circuit_enabled": true,
          "circuit_condition": {"comparator": ">", "constant": 0, "first_signal": {"name": "signal-everything", "type": "virtual"}}
        },
        "position": {"x": -0.5, "y": 5.5}
      },
      {
        "name": "bulk-inserter",
        "direction": 8,
        "use_filters": true,
        "control_behavior": {"circuit_set_filters": true},
        "position": {"x": -0.5, "y": 7.5}
      },
      {
        "name": "bulk-inserter",
        "use_filters": true,
        "control_behavior": {"circuit_set_filters": true},
        "position": {"x": -0.5, "y": 10.5}
      },
      {
        "name": "bulk-inserter",
        "control_behavior": {
          "circuit_enabled": true,
          "circuit_condition": {"comparator": ">", "constant": 0, "first_signal": {"name": "signal-everything", "type": "virtual"}}
        },
        "position": {"x": -0.5, "y": 12.5}
      },
      {
        "name": "bulk-inserter",
        "direction": 8,
        "control_behavior": {
          "circuit_enabled": true,
          "circuit_condition": {"comparator": ">", "constant": 0, "first_signal": {"name": "signal-everything", "type": "virtual"}}
        },
        "position": {"x": 0.5, "y": 5.5}
      },
      {
        "name": "bulk-inserter",
        "direction": 8,
        "control_behavior": {
          "circuit_enabled": true,
          "circuit_condition": {"comparator": ">", "constant": 0, "first_signal": {"name": "signal-everything", "type": "virtual"}}
        },
        "position": {"x": 1.5, "y": 5.5}
      },
      {
        "name": "bulk-inserter",
        "direction": 8,
        "control_behavior": {
          "circuit_enabled": true,
          "circuit_condition": {"comparator": ">", "constant": 0, "first_signal": {"name": "signal-everything", "type": "virtual"}}
        },
        "position": {"x": 2.5, "y": 5.5}
      },
      {
        "name": "bulk-inserter",
        "direction": 8,
        "control_behavior": {
          "circuit_enabled": true,
          "circuit_condition": {"comparator": ">", "constant": 0, "first_signal": {"name": "signal-everything", "type": "virtual"}}
        },
        "position": {"x": 3.5, "y": 5.5}
      },
      {
        "name": "bulk-inserter",
        "direction": 8,
        "use_filters": true,
        "control_behavior": {"circuit_set_filters": true},
        "position": {"x": 0.5, "y": 7.5}
      },
      {
        "name": "bulk-inserter",
        "direction": 8,
        "use_filters": true,
        "control_behavior": {"circuit_set_filters": true},
        "position": {"x": 1.5, "y": 7.5}
      },
      {
        "name": "bulk-inserter",
        "direction": 8,
        "use_filters": true,
        "control_behavior": {"circuit_set_filters": true},
        "position": {"x": 2.5, "y": 7.5}
      },
      {
        "name": "bulk-inserter",
        "direction": 8,
        "use_filters": true,
        "control_behavior": {"circuit_set_filters": true},
        "position": {"x": 3.5, "y": 7.5}
      },
      {
        "name": "bulk-inserter",
        "direction": 8,
        "control_behavior": {
          "circuit_enabled": true,
          "circuit_condition": {"comparator": ">", "constant": 0, "first_signal": {"name": "signal-everything", "type": "virtual"}}
        },
        "position": {"x": 4.5, "y": 5.5}
      },
      {
        "name": "bulk-inserter",
        "direction": 8,
        "control_behavior": {
          "circuit_enabled": true,
          "circuit_condition": {"comparator": ">", "constant": 0, "first_signal": {"name": "signal-everything", "type": "virtual"}}
        },
        "position": {"x": 6.5, "y": 5.5}
      },
      {
        "name": "bulk-inserter",
        "direction": 8,
        "control_behavior": {
          "circuit_enabled": true,
          "circuit_condition": {"comparator": ">", "constant": 0, "first_signal": {"name": "signal-everything", "type": "virtual"}}
        },
        "position": {"x": 7.5, "y": 5.5}
      },
      {
        "name": "bulk-inserter",
        "direction": 8,
        "use_filters": true,
        "control_behavior": {"circuit_set_filters": true},
        "position": {"x": 4.5, "y": 7.5}
      },
      {
        "name": "bulk-inserter",
        "direction": 8,
        "use_filters": true,
        "control_behavior": {"circuit_set_filters": true},
        "position": {"x": 6.5, "y": 7.5}
      },
      {
        "name": "bulk-inserter",
        "direction": 8,
        "use_filters": true,
        "control_behavior": {"circuit_set_filters": true},
        "position": {"x": 7.5, "y": 7.5}
      },
      {
        "name": "bulk-inserter",
        "direction": 8,
        "control_behavior": {
          "circuit_enabled": true,
          "circuit_condition": {"comparator": ">", "constant": 0, "first_signal": {"name": "signal-everything", "type": "virtual"}}
        },
        "position": {"x": 8.5, "y": 5.5}
      },
      {
        "name": "bulk-inserter",
        "direction": 8,
        "control_behavior": {
          "circuit_enabled": true,
          "circuit_condition": {"comparator": ">", "constant": 0, "first_signal": {"name": "signal-everything", "type": "virtual"}}
        },
        "position": {"x": 9.5, "y": 5.5}
      },
      {
        "name": "bulk-inserter",
        "direction": 8,
        "control_behavior": {
          "circuit_enabled": true,
          "circuit_condition": {"comparator": ">", "constant": 0, "first_signal": {"name": "signal-everything", "type": "virtual"}}
        },
        "position": {"x": 10.5, "y": 5.5}
      },
      {
        "name": "bulk-inserter",
        "direction": 8,
        "control_behavior": {
          "circuit_enabled": true,
          "circuit_condition": {"comparator": ">", "constant": 0, "first_signal": {"name": "signal-everything", "type": "virtual"}}
        },
        "position": {"x": 11.5, "y": 5.5}
      },
      {
        "name": "bulk-inserter",
        "direction": 8,
        "use_filters": true,
        "control_behavior": {"circuit_set_filters": true},
        "position": {"x": 8.5, "y": 7.5}
      },
      {
        "name": "bulk-inserter",
        "direction": 8,
        "use_filters": true,
        "control_behavior": {"circuit_set_filters": true},
        "position": {"x": 9.5, "y": 7.5}
      },
      {
        "name": "bulk-inserter",
        "direction": 8,
        "use_filters": true,
        "control_behavior": {"circuit_set_filters": true},
        "position": {"x": 10.5, "y": 7.5}
      },
      {
        "name": "bulk-inserter",
        "direction": 8,
        "use_filters": true,
        "control_behavior": {"circuit_set_filters": true},
        "position": {"x": 11.5, "y": 7.5}
      },
      {
        "name": "bulk-inserter",
        "use_filters": true,
        "control_behavior": {"circuit_set_filters": true},
        "position": {"x": 0.5, "y": 10.5}
      },
      {
        "name": "bulk-inserter",
        "use_filters": true,
        "control_behavior": {"circuit_set_filters": true},
        "position": {"x": 1.5, "y": 10.5}
      },
      {
        "name": "bulk-inserter",
        "use_filters": true,
        "control_behavior": {"circuit_set_filters": true},
        "position": {"x": 2.5, "y": 10.5}
      },
      {
        "name": "bulk-inserter",
        "use_filters": true,
        "control_behavior": {"circuit_set_filters": true},
        "position": {"x": 3.5, "y": 10.5}
      },
      {
        "name": "bulk-inserter",
        "use_filters": true,
        "control_behavior": {"circuit_set_filters": true},
        "position": {"x": 4.5, "y": 10.5}
      },
      {
        "name": "bulk-inserter",
        "use_filters": true,
        "control_behavior": {"circuit_set_filters": true},
        "position": {"x": 6.5, "y": 10.5}
      },
      {
        "name": "bulk-inserter",
        "use_filters": true,
        "control_behavior": {"circuit_set_filters": true},
        "position": {"x": 7.5, "y": 10.5}
      },
      {
        "name": "bulk-inserter",
        "control_behavior": {
          "circuit_enabled": true,
          "circuit_condition": {"comparator": ">", "constant": 0, "first_signal": {"name": "signal-everything", "type": "virtual"}}
        },
        "position": {"x": 0.5, "y": 12.5}
      },
      {
        "name": "bulk-inserter",
        "control_behavior": {
          "circuit_enabled": true,
          "circuit_condition": {"comparator": ">", "constant": 0, "first_signal": {"name": "signal-everything", "type": "virtual"}}
        },
        "position": {"x": 1.5, "y": 12.5}
      },
      {
        "name": "bulk-inserter",
        "control_behavior": {
          "circuit_enabled": true,
          "circuit_condition": {"comparator": ">", "constant": 0, "first_signal": {"name": "signal-everything", "type": "virtual"}}
        },
        "position": {"x": 2.5, "y": 12.5}
      },
      {
        "name": "bulk-inserter",
        "control_behavior": {
          "circuit_enabled": true,
          "circuit_condition": {"comparator": ">", "constant": 0, "first_signal": {"name": "signal-everything", "type": "virtual"}}
        },
        "position": {"x": 3.5, "y": 12.5}
      },
      {
        "name": "bulk-inserter",
        "control_behavior": {
          "circuit_enabled": true,
          "circuit_condition": {"comparator": ">", "constant": 0, "first_signal": {"name": "signal-everything", "type": "virtual"}}
        },
        "position": {"x": 4.5, "y": 12.5}
      },
      {
        "name": "bulk-inserter",
        "control_behavior": {
          "circuit_enabled": true,
          "circuit_condition": {"comparator": ">", "constant": 0, "first_signal": {"name": "signal-everything", "type": "virtual"}}
        },
        "position": {"x": 6.5, "y": 12.5}
      },
      {
        "name": "bulk-inserter",
        "control_behavior": {
          "circuit_enabled": true,
          "circuit_condition": {"comparator": ">", "constant": 0, "first_signal": {"name": "signal-everything", "type": "virtual"}}
        },
        "position": {"x": 7.5, "y": 12.5}
      },
      {
        "name": "bulk-inserter",
        "use_filters": true,
        "control_behavior": {"circuit_set_filters": true},
        "position": {"x": 8.5, "y": 10.5}
      },
      {
        "name": "bulk-inserter",
        "use_filters": true,
        "control_behavior": {"circuit_set_filters": true},
        "position": {"x": 9.5, "y": 10.5}
      },
      {
        "name": "bulk-inserter",
        "use_filters": true,
        "control_behavior": {"circuit_set_filters": true},
        "position": {"x": 10.5, "y": 10.5}
      },
      {
        "name": "bulk-inserter",
        "use_filters": true,
        "control_behavior": {"circuit_set_filters": true},
        "position": {"x": 11.5, "y": 10.5}
      },
      {
        "name": "bulk-inserter",
        "control_behavior": {
          "circuit_enabled": true,
          "circuit_condition": {"comparator": ">", "constant": 0, "first_signal": {"name": "signal-everything", "type": "virtual"}}
        },
        "position": {"x": 8.5, "y": 12.5}
      },
      {
        "name": "bulk-inserter",
        "control_behavior": {
          "circuit_enabled": true,
          "circuit_condition": {"comparator": ">", "constant": 0, "first_signal": {"name": "signal-everything", "type": "virtual"}}
        },
        "position": {"x": 9.5, "y": 12.5}
      },
      {
        "name": "bulk-inserter",
        "control_behavior": {
          "circuit_enabled": true,
          "circuit_condition": {"comparator": ">", "constant": 0, "first_signal": {"name": "signal-everything", "type": "virtual"}}
        },
        "position": {"x": 10.5, "y": 12.5}
      },
      {
        "name": "bulk-inserter",
        "control_behavior": {
          "circuit_enabled": true,
          "circuit_condition": {"comparator": ">", "constant": 0, "first_signal": {"name": "signal-everything", "type": "virtual"}}
        },
        "position": {"x": 11.5, "y": 12.5}
      },
      {
        "name": "constant-combinator",
        "direction": 4,
        "control_behavior": {
          "sections": {
            "sections": [
              {
                "index": 1,
                "filters": [
                  {
                    "name": "signal-R",
                    "comparator": "=",
                    "count": 0,
                    "index": 1,
                    "quality": "normal",
                    "type": "virtual"
                  },
                  {
                    "name": "signal-E",
                    "comparator": "=",
                    "count": 0,
                    "index": 2,
                    "quality": "normal",
                    "type": "virtual"
                  },
                  {
                    "name": "signal-Q",
                    "comparator": "=",
                    "count": 0,
                    "index": 3,
                    "quality": "normal",
                    "type": "virtual"
                  },
                  {"name": "parameter-0", "comparator": "=", "count": -1, "index": 4, "quality": "normal"}
                ]
              },
              {
                "group": "BT:2car",
                "index": 2,
                "filters": [
                  {
                    "name": "signal-C",
                    "comparator": "=",
                    "count": 2,
                    "index": 1,
                    "quality": "normal",
                    "type": "virtual"
                  },
                  {
                    "name": "signal-M",
                    "comparator": "=",
                    "count": 256,
                    "index": 2,
                    "quality": "normal",
                    "type": "virtual"
                  },
                  {
                    "name": "signal-S",
                    "comparator": "=",
                    "count": 80,
                    "index": 3,
                    "quality": "normal",
                    "type": "virtual"
                  },
                  {
                    "name": "signal-T",
                    "comparator": "=",
                    "count": -80,
                    "index": 4,
                    "max_count": 4294967216,
                    "quality": "normal",
                    "type": "virtual"
                  },
                  {
                    "name": "signal-F",
                    "comparator": "=",
                    "count": 100000,
                    "index": 5,
                    "quality": "normal",
                    "type": "virtual"
                  },
                  {
                    "name": "signal-G",
                    "comparator": "=",
                    "count": -100000,
                    "index": 6,
                    "max_count": 4294867296,
                    "quality": "normal",
                    "type": "virtual"
                  },
                  {
                    "name": "signal-L",
                    "comparator": "=",
                    "count": 4,
                    "index": 7,
                    "quality": "normal",
                    "type": "virtual"
                  }
                ]
              }
            ]
          }
        },
        "position": {"x": -2.5, "y": 10.5}
      },
      {"name": "iron-chest", "position": {"x": -0.5, "y": 6.5}},
      {"name": "iron-chest", "position": {"x": -0.5, "y": 11.5}},
      {"name": "iron-chest", "position": {"x": 0.5, "y": 6.5}},
      {"name": "iron-chest", "position": {"x": 1.5, "y": 6.5}},
      {"name": "iron-chest", "position": {"x": 2.5, "y": 6.5}},
      {"name": "iron-chest", "position": {"x": 3.5, "y": 6.5}},
      {"name": "iron-chest", "position": {"x": 4.5, "y": 6.5}},
      {"name": "iron-chest", "position": {"x": 6.5, "y": 6.5}},
      {"name": "iron-chest", "position": {"x": 7.5, "y": 6.5}},
      {"name": "iron-chest", "position": {"x": 8.5, "y": 6.5}},
      {"name": "iron-chest", "position": {"x": 9.5, "y": 6.5}},
      {"name": "iron-chest", "position": {"x": 10.5, "y": 6.5}},
      {"name": "iron-chest", "position": {"x": 11.5, "y": 6.5}},
      {"name": "iron-chest", "position": {"x": 0.5, "y": 11.5}},
      {"name": "iron-chest", "position": {"x": 1.5, "y": 11.5}},
      {"name": "iron-chest", "position": {"x": 2.5, "y": 11.5}},
      {"name": "iron-chest", "position": {"x": 3.5, "y": 11.5}},
      {"name": "iron-chest", "position": {"x": 4.5, "y": 11.5}},
      {"name": "iron-chest", "position": {"x": 6.5, "y": 11.5}},
      {"name": "iron-chest", "position": {"x": 7.5, "y": 11.5}},
      {"name": "iron-chest", "position": {"x": 8.5, "y": 11.5}},
      {"name": "iron-chest", "position": {"x": 9.5, "y": 11.5}},
      {"name": "iron-chest", "position": {"x": 10.5, "y": 11.5}},
      {"name": "iron-chest", "position": {"x": 11.5, "y": 11.5}},
      {"name": "medium-electric-pole", "position": {"x": -6.5, "y": 5.5}},
      {"name": "medium-electric-pole", "position": {"x": -1.5, "y": 7.5}},
      {"name": "medium-electric-pole", "position": {"x": -1.5, "y": 10.5}},
      {"name": "medium-electric-pole", "position": {"x": 5.5, "y": 7.5}},
      {"name": "medium-electric-pole", "position": {"x": 12.5, "y": 7.5}},
      {"name": "medium-electric-pole", "position": {"x": 5.5, "y": 10.5}},
      {"name": "medium-electric-pole", "position": {"x": 12.5, "y": 10.5}},
      {"name": "splitter", "direction": 12, "position": {"x": 1.5, "y": 0}},
      {"name": "splitter", "direction": 12, "position": {"x": 3.5, "y": 2}},
      {"name": "splitter", "input_priority": "left", "position": {"x": 5, "y": 3.5}},
      {"name": "splitter", "direction": 12, "position": {"x": 10.5, "y": 2}},
      {"name": "splitter", "input_priority": "left", "position": {"x": 12, "y": 3.5}},
      {"name": "straight-rail", "direction": 4, "position": {"x": -8, "y": 9}},
      {"name": "straight-rail", "direction": 4, "position": {"x": -6, "y": 9}},
      {"name": "straight-rail", "direction": 4, "position": {"x": -4, "y": 9}},
      {"name": "straight-rail", "direction": 4, "position": {"x": -2, "y": 9}},
      {"name": "straight-rail", "direction": 4, "position": {"x": 0, "y": 9}},
      {"name": "straight-rail", "direction": 4, "position": {"x": 2, "y": 9}},
      {"name": "straight-rail", "direction": 4, "position": {"x": 4, "y": 9}},
      {"name": "straight-rail", "direction": 4, "position": {"x": 6, "y": 9}},
      {"name": "straight-rail", "direction": 4, "position": {"x": 8, "y": 9}},
      {"name": "straight-rail", "direction": 4, "position": {"x": 10, "y": 9}},
      {"name": "straight-rail", "direction": 4, "position": {"x": 12, "y": 9}},
      {
        "name": "train-stop",
        "direction": 12,
        "manual_trains_limit": 0,
        "station": "[virtual-signal=down-arrow][virtual-signal=signal-2][item=parameter-0]",
        "color": {"a": 0.49803921580314636, "b": 1, "g": 0.49803921580314636, "r": 0},
        "control_behavior": {
          "circuit_enabled": true,
          "set_trains_limit": true,
          "circuit_condition": {"comparator": ">", "constant": 0, "first_signal": {"name": "signal-L", "type": "virtual"}},
          "train_stopped_signal": {"name": "signal-T", "type": "virtual"},
          "trains_limit_signal": {"name": "signal-L", "type": "virtual"}
        },
        "position": {"x": -8, "y": 7}
      },
      {"name": "transport-belt", "direction": 12, "position": {"x": 0.5, "y": -0.5}},
      {"name": "transport-belt", "direction": 12, "position": {"x": 2.5, "y": -0.5}},
      {"name": "transport-belt", "direction": 12, "position": {"x": 3.5, "y": -0.5}},
      {"name": "transport-belt", "direction": 12, "position": {"x": 4.5, "y": -0.5}},
      {"name": "transport-belt", "direction": 12, "position": {"x": 5.5, "y": -0.5}},
      {"name": "transport-belt", "direction": 12, "position": {"x": 6.5, "y": -0.5}},
      {"name": "transport-belt", "direction": 12, "position": {"x": 7.5, "y": -0.5}},
      {"name": "transport-belt", "direction": 12, "position": {"x": 8.5, "y": -0.5}},
      {"name": "transport-belt", "direction": 12, "position": {"x": 9.5, "y": -0.5}},
      {"name": "transport-belt", "direction": 4, "position": {"x": -0.5, "y": 4.5}},
      {"name": "transport-belt", "direction": 4, "position": {"x": -0.5, "y": 13.5}},
      {"name": "transport-belt", "direction": 12, "position": {"x": 0.5, "y": 0.5}},
      {"name": "transport-belt", "direction": 12, "position": {"x": 2.5, "y": 0.5}},
      {"name": "transport-belt", "position": {"x": 2.5, "y": 1.5}},
      {"name": "transport-belt", "direction": 4, "position": {"x": 0.5, "y": 3.5}},
      {"name": "transport-belt", "direction": 4, "position": {"x": 1.5, "y": 3.5}},
      {"name": "transport-belt", "position": {"x": 2.5, "y": 2.5}},
      {"name": "transport-belt", "direction": 8, "position": {"x": 2.5, "y": 3.5}},
      {"name": "transport-belt", "position": {"x": 5.5, "y": 2.5}},
      {"name": "transport-belt", "direction": 4, "position": {"x": 7.5, "y": 3.5}},
      {"name": "transport-belt", "direction": 4, "position": {"x": 0.5, "y": 4.5}},
      {"name": "transport-belt", "position": {"x": 1.5, "y": 4.5}},
      {"name": "transport-belt", "direction": 4, "position": {"x": 2.5, "y": 4.5}},
      {"name": "transport-belt", "direction": 4, "position": {"x": 3.5, "y": 4.5}},
      {"name": "transport-belt", "position": {"x": 4.5, "y": 4.5}},
      {"name": "transport-belt", "position": {"x": 5.5, "y": 4.5}},
      {"name": "transport-belt", "position": {"x": 5.5, "y": 5.5}},
      {"name": "transport-belt", "direction": 4, "position": {"x": 6.5, "y": 4.5}},
      {"name": "transport-belt", "direction": 4, "position": {"x": 7.5, "y": 4.5}},
      {"name": "transport-belt", "position": {"x": 9.5, "y": 0.5}},
      {"name": "transport-belt", "position": {"x": 9.5, "y": 1.5}},
      {"name": "transport-belt", "position": {"x": 9.5, "y": 2.5}},
      {"name": "transport-belt", "direction": 4, "position": {"x": 8.5, "y": 3.5}},
      {"name": "transport-belt", "direction": 8, "position": {"x": 9.5, "y": 3.5}},
      {"name": "transport-belt", "position": {"x": 12.5, "y": 2.5}},
      {"name": "transport-belt", "position": {"x": 8.5, "y": 4.5}},
      {"name": "transport-belt", "direction": 4, "position": {"x": 9.5, "y": 4.5}},
      {"name": "transport-belt", "direction": 4, "position": {"x": 10.5, "y": 4.5}},
      {"name": "transport-belt", "position": {"x": 11.5, "y": 4.5}},
      {"name": "transport-belt", "position": {"x": 12.5, "y": 4.5}},
      {"name": "transport-belt", "position": {"x": 12.5, "y": 5.5}},
      {"name": "transport-belt", "direction": 4, "position": {"x": 0.5, "y": 13.5}},
      {"name": "transport-belt", "direction": 8, "position": {"x": 1.5, "y": 13.5}},
      {"name": "transport-belt", "direction": 4, "position": {"x": 2.5, "y": 13.5}},
      {"name": "transport-belt", "direction": 4, "position": {"x": 3.5, "y": 13.5}},
      {"name": "transport-belt", "direction": 4, "position": {"x": 0.5, "y": 14.5}},
      {"name": "transport-belt", "direction": 4, "position": {"x": 1.5, "y": 14.5}},
      {"name": "transport-belt", "position": {"x": 2.5, "y": 14.5}},
      {"name": "transport-belt", "position": {"x": 5.5, "y": 12.5}},
      {"name": "transport-belt", "direction": 4, "position": {"x": 4.5, "y": 13.5}},
      {"name": "transport-belt", "position": {"x": 5.5, "y": 13.5}},
      {"name": "transport-belt", "direction": 4, "position": {"x": 6.5, "y": 13.5}},
      {"name": "transport-belt", "direction": 4, "position": {"x": 7.5, "y": 13.5}},
      {"name": "transport-belt", "direction": 4, "position": {"x": 7.5, "y": 14.5}},
      {"name": "transport-belt", "direction": 8, "position": {"x": 8.5, "y": 13.5}},
      {"name": "transport-belt", "direction": 4, "position": {"x": 9.5, "y": 13.5}},
      {"name": "transport-belt", "direction": 4, "position": {"x": 10.5, "y": 13.5}},
      {"name": "transport-belt", "direction": 4, "position": {"x": 11.5, "y": 13.5}},
      {"name": "transport-belt", "direction": 4, "position": {"x": 8.5, "y": 14.5}},
      {"name": "transport-belt", "position": {"x": 9.5, "y": 14.5}},
      {"name": "transport-belt", "position": {"x": 12.5, "y": 12.5}},
      {"name": "transport-belt", "position": {"x": 12.5, "y": 13.5}},
      {"name": "underground-belt", "direction": 12, "type": "output", "position": {"x": 4.5, "y": 1.5}},
      {"name": "underground-belt", "direction": 12, "type": "input", "position": {"x": 5.5, "y": 1.5}},
      {"name": "underground-belt", "direction": 12, "type": "output", "position": {"x": 4.5, "y": 2.5}},
      {"name": "underground-belt", "type": "output", "position": {"x": 5.5, "y": 6.5}},
      {"name": "underground-belt", "direction": 12, "type": "output", "position": {"x": 11.5, "y": 1.5}},
      {"name": "underground-belt", "direction": 12, "type": "output", "position": {"x": 11.5, "y": 2.5}},
      {"name": "underground-belt", "direction": 12, "type": "input", "position": {"x": 12.5, "y": 1.5}},
      {"name": "underground-belt", "type": "output", "position": {"x": 12.5, "y": 6.5}},
      {"name": "underground-belt", "type": "input", "position": {"x": 5.5, "y": 11.5}},
      {"name": "underground-belt", "type": "input", "position": {"x": 12.5, "y": 11.5}}
    ],
    "icons": [
      {"index": 1, "signal": {"name": "cargo-wagon"}},
      {"index": 2, "signal": {"name": "transport-belt"}},
      {"index": 3, "signal": {"name": "signal-2", "type": "virtual"}},
      {"index": 4, "signal": {"name": "signal-R", "type": "virtual"}}
    ],
    "parameters": [
      {
        "name": "What is being requested?",
        "id": "parameter-0",
        "type": "id",
        "quality-condition": {"comparator": "=", "quality": "normal"}
      }
    ],
    "wires": [
      ["0,5.5", 5, "3.5,6", 5],
      ["3.5,6", 5, "8.5,8", 5],
      ["10.5,6", 1, "10.5,7", 1],
      ["10.5,6", 2, "9.5,6", 2],
      ["10.5,6", 2, "11.5,6", 2],
      ["9.5,6", 1, "9.5,7", 1],
      ["9.5,6", 2, "7.5,6.5", 4],
      ["9.5,6", 2, "9.5,13", 2],
      ["12.5,6", 1, "12.5,7", 1],
      ["12.5,6", 2, "11.5,6", 2],
      ["12.5,6", 2, "13.5,6", 2],
      ["11.5,6", 1, "11.5,7", 1],
      ["14.5,6", 1, "14.5,7", 1],
      ["14.5,6", 2, "13.5,6", 2],
      ["14.5,6", 2, "16.5,6", 2],
      ["13.5,6", 1, "13.5,7", 1],
      ["16.5,6", 1, "16.5,7", 1],
      ["16.5,6", 2, "17.5,6", 2],
      ["18.5,6", 1, "18.5,7", 1],
      ["18.5,6", 2, "17.5,6", 2],
      ["18.5,6", 2, "19.5,6", 2],
      ["17.5,6", 1, "17.5,7", 1],
      ["20.5,6", 1, "20.5,7", 1],
      ["20.5,6", 2, "19.5,6", 2],
      ["20.5,6", 2, "21.5,6", 2],
      ["19.5,6", 1, "19.5,7", 1],
      ["21.5,6", 1, "21.5,7", 1],
      ["8.5,8", 1, "9.5,8", 1],
      ["8.5,8", 2, "7.5,6.5", 2],
      ["8.5,8", 2, "9.5,7", 2],
      ["8.5,8", 5, "15.5,8", 5],
      ["8.5,8", 5, "8.5,11", 5],
      ["10.5,7", 2, "9.5,7", 2],
      ["10.5,7", 2, "11.5,7", 2],
      ["9.5,7", 2, "9.5,12", 2],
      ["9.5,8", 1, "10.5,8", 1],
      ["9.5,8", 1, "9.5,11", 1],
      ["10.5,8", 1, "11.5,8", 1],
      ["12.5,7", 2, "11.5,7", 2],
      ["12.5,7", 2, "13.5,7", 2],
      ["11.5,8", 1, "12.5,8", 1],
      ["12.5,8", 1, "13.5,8", 1],
      ["14.5,7", 2, "13.5,7", 2],
      ["14.5,7", 2, "16.5,7", 2],
      ["14.5,8", 1, "13.5,8", 1],
      ["14.5,8", 1, "16.5,8", 1],
      ["16.5,7", 2, "17.5,7", 2],
      ["16.5,8", 1, "17.5,8", 1],
      ["15.5,8", 5, "22.5,8", 5],
      ["15.5,8", 5, "15.5,11", 5],
      ["18.5,7", 2, "17.5,7", 2],
      ["18.5,7", 2, "19.5,7", 2],
      ["18.5,8", 1, "17.5,8", 1],
      ["18.5,8", 1, "19.5,8", 1],
      ["20.5,7", 2, "19.5,7", 2],
      ["20.5,7", 2, "21.5,7", 2],
      ["20.5,8", 1, "19.5,8", 1],
      ["20.5,8", 1, "21.5,8", 1],
      ["22.5,8", 5, "22.5,11", 5],
      ["8.5,11", 1, "7.5,11", 1],
      ["8.5,11", 5, "15.5,11", 5],
      ["10.5,12", 1, "10.5,13", 1],
      ["10.5,12", 2, "9.5,12", 2],
      ["10.5,12", 2, "11.5,12", 2],
      ["9.5,12", 1, "9.5,13", 1],
      ["9.5,11", 1, "10.5,11", 1],
      ["10.5,11", 1, "11.5,11", 1],
      ["12.5,12", 1, "12.5,13", 1],
      ["12.5,12", 2, "11.5,12", 2],
      ["12.5,12", 2, "13.5,12", 2],
      ["11.5,12", 1, "11.5,13", 1],
      ["12.5,11", 1, "11.5,11", 1],
      ["12.5,11", 1, "13.5,11", 1],
      ["14.5,12", 1, "14.5,13", 1],
      ["14.5,12", 2, "13.5,12", 2],
      ["14.5,12", 2, "16.5,12", 2],
      ["13.5,12", 1, "13.5,13", 1],
      ["13.5,11", 1, "14.5,11", 1],
      ["14.5,11", 1, "16.5,11", 1],
      ["16.5,12", 1, "16.5,13", 1],
      ["16.5,12", 2, "17.5,12", 2],
      ["16.5,11", 1, "17.5,11", 1],
      ["15.5,11", 5, "22.5,11", 5],
      ["18.5,12", 1, "18.5,13", 1],
      ["18.5,12", 2, "17.5,12", 2],
      ["18.5,12", 2, "19.5,12", 2],
      ["17.5,12", 1, "17.5,13", 1],
      ["18.5,11", 1, "17.5,11", 1],
      ["18.5,11", 1, "19.5,11", 1],
      ["20.5,12", 1, "20.5,13", 1],
      ["20.5,12", 2, "19.5,12", 2],
      ["20.5,12", 2, "21.5,12", 2],
      ["19.5,12", 1, "19.5,13", 1],
      ["20.5,11", 1, "19.5,11", 1],
      ["20.5,11", 1, "21.5,11", 1],
      ["21.5,12", 1, "21.5,13", 1],
      ["10.5,13", 2, "9.5,13", 2],
      ["10.5,13", 2, "11.5,13", 2],
      ["12.5,13", 2, "11.5,13", 2],
      ["12.5,13", 2, "13.5,13", 2],
      ["14.5,13", 2, "13.5,13", 2],
      ["14.5,13", 2, "16.5,13", 2],
      ["16.5,13", 2, "17.5,13", 2],
      ["18.5,13", 2, "17.5,13", 2],
      ["18.5,13", 2, "19.5,13", 2],
      ["20.5,13", 2, "19.5,13", 2],
      ["20.5,13", 2, "21.5,13", 2]
    ]
  }
}
